supervisord_nagios-0.1.2-nspkg.pth
supervisord_nagios-0.1.2.dist-info/DESCRIPTION.rst
supervisord_nagios-0.1.2.dist-info/namespace_packages.txt
supervisord_nagios-0.1.2.dist-info/top_level.txt
supervisord_nagios-0.1.2.dist-info/WHEEL
supervisord_nagios-0.1.2.dist-info/METADATA
supervisord_nagios-0.1.2.dist-info/metadata.json
supervisord_nagios-0.1.2.dist-info/RECORD
supervisord_nagios/controllerplugin.py
