Metadata-Version: 2.0
Name: supervisord-nagios
Version: 0.1.2
Summary: nagios checks for supervisord services
Home-page: http://github.com/3dna/supervisord-nagios
Author: Jeremy Kitchen
Author-email: jeremy@nationbuilder.com
License: BSD-3
Keywords: nagios,supervisord
Platform: UNKNOWN
Requires-Dist: distribute
Requires-Dist: supervisor
